{
    "editor.fontSize": 14,
    "editor.wordWrap": "on",
    "latex-workshop.view.pdf.viewer": "tab",
    "spellright.language": [
        "en"
    ],
    "spellright.documentTypes": [
        "markdown",
        "latex",
        "plaintext"
    ],
    "latex-workshop.latex.clean.fileTypes": [
        "*.aux",
        "*.bbl",
        "*.blg",
        "*.idx",
        "*.ind",
        "*.lof",
        "*.lot",
        "*.out",
        "*.toc",
        "*.acn",
        "*.acr",
        "*.alg",
        "*.glg",
        "*.glo",
        "*.gls",
        "*.ist",
        "*.fls",
        "*.log",
        "*.fdb_latexmk",
        "*.cpt"
    ],
    "latex-workshop.latex.autoClean.run": "onBuilt",
    "editor.fontFamily": "'Source Han Mono SC', Menlo, Monaco, 'Courier New', monospace"
}